{
    "version": "0.8.1",
    "architecture": {
        "32bit": {
            "url": "https://github.com/goto/compass/releases/download/v0.8.1/compass_Windows_i386.zip",
            "bin": [
                "compass.exe"
            ],
            "hash": "e7f4adc4ab107bc736dae79d212356826cfa83d66210853ff806893e495e502a"
        },
        "64bit": {
            "url": "https://github.com/goto/compass/releases/download/v0.8.1/compass_Windows_x86_64.zip",
            "bin": [
                "compass.exe"
            ],
            "hash": "c66763d997b9299842029b4740236e5a46c7fdd566b8b228dc3b36c449462b40"
        },
        "arm64": {
            "url": "https://github.com/goto/compass/releases/download/v0.8.1/compass_Windows_arm64.zip",
            "bin": [
                "compass.exe"
            ],
            "hash": "4eb2a75492a216e112b8287b4501b77e02fc18daacb629cacd2d6162b4ed2bb0"
        }
    },
    "homepage": "https://github.com/goto/compass",
    "license": "Apache 2.0",
    "description": "Metadata Discovery and Lineage Service"
}