{
    "version": "0.7.6",
    "architecture": {
        "32bit": {
            "url": "https://github.com/goto/compass/releases/download/v0.7.6/compass_Windows_i386.zip",
            "bin": [
                "compass.exe"
            ],
            "hash": "061925d750e67906f65d999a8b608743e091fba65f47e011080c898556fced0e"
        },
        "64bit": {
            "url": "https://github.com/goto/compass/releases/download/v0.7.6/compass_Windows_x86_64.zip",
            "bin": [
                "compass.exe"
            ],
            "hash": "1cac62e7fbd5d9614400753d92364fa78c1d51317c6807af70a20604a83a16cb"
        },
        "arm64": {
            "url": "https://github.com/goto/compass/releases/download/v0.7.6/compass_Windows_arm64.zip",
            "bin": [
                "compass.exe"
            ],
            "hash": "68f4f6458926db1b45e25ea58a39487c5e1293f435bfa510d76990adba1abb8c"
        }
    },
    "homepage": "https://github.com/goto/compass",
    "license": "Apache 2.0",
    "description": "Metadata Discovery and Lineage Service"
}