{
    "version": "0.12.15-alpha.36",
    "architecture": {
        "32bit": {
            "url": "https://github.com/goto/guardian/releases/download/v0.12.15-alpha.36/guardian_0.12.15-alpha.36_Windows_i386.zip",
            "bin": [
                "guardian.exe"
            ],
            "hash": "ebeda86ab2ceb1816111101e5168aa19a99cf7ab23ad66dd78feb8cdad130633"
        },
        "64bit": {
            "url": "https://github.com/goto/guardian/releases/download/v0.12.15-alpha.36/guardian_0.12.15-alpha.36_Windows_x86_64.zip",
            "bin": [
                "guardian.exe"
            ],
            "hash": "b17ced98e39f6ba1b351fcf106f7040adddc49e2d653441f05a49d125d20def8"
        },
        "arm64": {
            "url": "https://github.com/goto/guardian/releases/download/v0.12.15-alpha.36/guardian_0.12.15-alpha.36_Windows_arm64.zip",
            "bin": [
                "guardian.exe"
            ],
            "hash": "e3e505e5bc0018510c91408f33c9e306c26db86d877716a53b58c6b5c3eb775b"
        }
    },
    "homepage": "https://github.com/goto/guardian",
    "license": "Apache 2.0",
    "description": "Universal data access tool"
}