{
    "version": "0.12.5-alpha.2",
    "architecture": {
        "32bit": {
            "url": "https://github.com/goto/guardian/releases/download/v0.12.5-alpha.2/guardian_0.12.5-alpha.2_Windows_i386.zip",
            "bin": [
                "guardian.exe"
            ],
            "hash": "a64bf7b0c130e7efd654bfa4151b87b33b12a4b0508db56fd7dea2d8a86a6f34"
        },
        "64bit": {
            "url": "https://github.com/goto/guardian/releases/download/v0.12.5-alpha.2/guardian_0.12.5-alpha.2_Windows_x86_64.zip",
            "bin": [
                "guardian.exe"
            ],
            "hash": "641d23a69435af0a657ba7471ee0aef8bd3deca8563253c0b807158ad7d6de72"
        },
        "arm64": {
            "url": "https://github.com/goto/guardian/releases/download/v0.12.5-alpha.2/guardian_0.12.5-alpha.2_Windows_arm64.zip",
            "bin": [
                "guardian.exe"
            ],
            "hash": "c8b320ef520565a6e35fe12212ee6687b281148136b63ad33e80b214687a0567"
        }
    },
    "homepage": "https://github.com/goto/guardian",
    "license": "Apache 2.0",
    "description": "Universal data access tool"
}