{
    "version": "0.12.15-alpha.25",
    "architecture": {
        "32bit": {
            "url": "https://github.com/goto/guardian/releases/download/v0.12.15-alpha.25/guardian_0.12.15-alpha.25_Windows_i386.zip",
            "bin": [
                "guardian.exe"
            ],
            "hash": "907f0b49fdcde8c646b353423e643a8669b7cba0b6bd0bd9a3300ed6a2ef0678"
        },
        "64bit": {
            "url": "https://github.com/goto/guardian/releases/download/v0.12.15-alpha.25/guardian_0.12.15-alpha.25_Windows_x86_64.zip",
            "bin": [
                "guardian.exe"
            ],
            "hash": "54a67b9056beead57b270f9092ba49df6f13e7e6d1e8ed40c54539885d6168e9"
        },
        "arm64": {
            "url": "https://github.com/goto/guardian/releases/download/v0.12.15-alpha.25/guardian_0.12.15-alpha.25_Windows_arm64.zip",
            "bin": [
                "guardian.exe"
            ],
            "hash": "4eee05724127c3333502e3466c8b39a35ac4caf6ee0e4e79d537ea5b5749f80a"
        }
    },
    "homepage": "https://github.com/goto/guardian",
    "license": "Apache 2.0",
    "description": "Universal data access tool"
}