{
    "version": "0.6.25-beta",
    "architecture": {
        "64bit": {
            "url": "https://github.com/goto/shield/releases/download/v0.6.25-beta/shield_Windows_x86_64.tar.gz",
            "bin": [
                "shield.exe"
            ],
            "hash": "3afa8b8ba38c90feb914301d176b6f20fee98c76181d3bfcb8db0e25cbecb345"
        },
        "arm64": {
            "url": "https://github.com/goto/shield/releases/download/v0.6.25-beta/shield_Windows_arm64.tar.gz",
            "bin": [
                "shield.exe"
            ],
            "hash": "4457700d3ec24a5d20b1012d2d4016a7318576e4d937f546fa7b85dbb8d409ad"
        }
    },
    "homepage": "https://github.com/goto/shield",
    "license": "Apache 2.0",
    "description": "Identity and authorization system"
}