{
    "version": "0.6.25",
    "architecture": {
        "64bit": {
            "url": "https://github.com/goto/shield/releases/download/v0.6.25/shield_Windows_x86_64.tar.gz",
            "bin": [
                "shield.exe"
            ],
            "hash": "4b9e4991d7c90bbd31f4821b2e38ed540802be175f330813983d8da5bdc38f6c"
        },
        "arm64": {
            "url": "https://github.com/goto/shield/releases/download/v0.6.25/shield_Windows_arm64.tar.gz",
            "bin": [
                "shield.exe"
            ],
            "hash": "dac8e545083bee3e01c7ec774c65a030a4e628af30c93656c2fa2b44adf54e78"
        }
    },
    "homepage": "https://github.com/goto/shield",
    "license": "Apache 2.0",
    "description": "Identity and authorization system"
}