{
    "version": "0.6.24-beta",
    "architecture": {
        "64bit": {
            "url": "https://github.com/goto/shield/releases/download/v0.6.24-beta/shield_Windows_x86_64.tar.gz",
            "bin": [
                "shield.exe"
            ],
            "hash": "8624106b3d0de7aefbe3c523dc31083f3f8b10fad94e8744ca3a2feba8f4c735"
        },
        "arm64": {
            "url": "https://github.com/goto/shield/releases/download/v0.6.24-beta/shield_Windows_arm64.tar.gz",
            "bin": [
                "shield.exe"
            ],
            "hash": "5ef039b96c913ca2c1d94aa92e39e4e5fc7f20272e882732926af46bee09a0b6"
        }
    },
    "homepage": "https://github.com/goto/shield",
    "license": "Apache 2.0",
    "description": "Identity and authorization system"
}